{"playerID": "01a799b5-60e7-4708-b9b9-107abd2af96e", "playerNames": [{"playerName": "jakubek_nr1", "sinceDate": "2021-04-15"}], "results": {"cotd": [{"date": "2021-04-15", "server": 23, "serverRank": 17, "globalRank": 1425, "totalPlayer": 2072}, {"date": "2021-04-17", "server": 22, "serverRank": 30, "globalRank": 1374, "totalPlayer": 1761}, {"date": "2021-04-21", "server": 17, "serverRank": "DNF", "globalRank": 1083, "totalPlayer": 2083}, {"date": "2021-04-23", "server": 22, "serverRank": 53, "globalRank": 1397, "totalPlayer": 1937}]}}