{"playerID": "0207f8cb-0568-4443-8d9b-63b276b1a6e3", "playerNames": [{"playerName": "mannero99", "sinceDate": "2021-02-09"}], "results": {"cotd": [{"date": "2020-11-23", "server": 20, "serverRank": 34, "globalRank": 1250, "totalPlayer": 1696}, {"date": "2020-11-27", "server": 19, "serverRank": 32, "globalRank": 1184, "totalPlayer": 1525}, {"date": "2020-11-28", "server": 11, "serverRank": 48, "globalRank": 688, "totalPlayer": 1364}, {"date": "2020-11-29", "server": 10, "serverRank": 11, "globalRank": 587, "totalPlayer": 1466}, {"date": "2020-11-30", "server": 19, "serverRank": 20, "globalRank": 1172, "totalPlayer": 1683}, {"date": "2020-12-01", "server": 17, "serverRank": 10, "globalRank": 1034, "totalPlayer": 1522}, {"date": "2020-12-03", "server": 16, "serverRank": 55, "globalRank": 1015, "totalPlayer": 1507}, {"date": "2020-12-09", "server": 20, "serverRank": "DNF", "globalRank": 1279, "totalPlayer": 1462}]}}