{"playerID": "17ef4ae3-b067-4eb6-a16b-e2124181b00f", "playerNames": [{"playerName": "Pumpkinnnnn.2", "sinceDate": "2021-03-16"}], "results": {"cotd": [{"date": "2021-03-16", "server": 21, "serverRank": 8, "globalRank": 1288, "totalPlayer": 1644}, {"date": "2021-03-18", "server": 18, "serverRank": 41, "globalRank": 1129, "totalPlayer": 1683}, {"date": "2021-03-19", "server": 18, "serverRank": 15, "globalRank": 1103, "totalPlayer": 1595}, {"date": "2021-03-20", "server": 18, "serverRank": 8, "globalRank": 1096, "totalPlayer": 1483}]}}