{"playerID": "1c18b7d5-a322-4f15-b572-c7e5f634c702", "playerNames": [{"playerName": "Ladefehler_404", "sinceDate": "2021-02-09"}], "results": {"cotd": [{"date": "2020-11-17", "server": 13, "serverRank": 47, "globalRank": 815, "totalPlayer": 1651}, {"date": "2020-11-18", "server": 7, "serverRank": 12, "globalRank": 396, "totalPlayer": 1684}, {"date": "2020-11-26", "server": 16, "serverRank": "DNF", "globalRank": 1017, "totalPlayer": 1512}, {"date": "2020-11-30", "server": 9, "serverRank": 47, "globalRank": 559, "totalPlayer": 1683}, {"date": "2020-12-15", "server": 8, "serverRank": 26, "globalRank": 474, "totalPlayer": 1496}, {"date": "2021-02-26", "server": 6, "serverRank": 58, "globalRank": 378, "totalPlayer": 1408}]}}