{"playerID": "2eee80b1-09f5-4a52-a8a6-955169e4b0d4", "playerNames": [{"playerName": "SnnIz.", "sinceDate": "2021-02-09"}], "results": {"cotd": [{"date": "2021-02-01", "server": 10, "serverRank": 23, "globalRank": 599, "totalPlayer": 1500}, {"date": "2021-02-06", "server": 8, "serverRank": 9, "globalRank": 457, "totalPlayer": 1080}, {"date": "2021-02-07", "server": 21, "serverRank": 41, "globalRank": 1321, "totalPlayer": 1374}, {"date": "2021-02-10", "server": 9, "serverRank": 48, "globalRank": 560, "totalPlayer": 1523}]}}