{"playerID": "320cbd14-8275-4ae3-a877-3582c2c0a63e", "playerNames": [{"playerName": "Arcosite", "sinceDate": "2021-03-22"}], "results": {"cotd": [{"date": "2021-03-22", "server": 13, "serverRank": 26, "globalRank": 794, "totalPlayer": 1748}, {"date": "2021-03-25", "server": 16, "serverRank": "DNF", "globalRank": 1020, "totalPlayer": 1766}, {"date": "2021-03-26", "server": 11, "serverRank": 9, "globalRank": 649, "totalPlayer": 1600}, {"date": "2021-03-27", "server": 14, "serverRank": 6, "globalRank": 838, "totalPlayer": 1582}]}}