{"playerID": "335ac057-f9ef-48fe-bd1e-ba7d8d92bbbb", "playerNames": [{"playerName": "NeySushi", "sinceDate": "2021-03-08"}], "results": {"cotd": [{"date": "2021-03-08", "server": 17, "serverRank": "DNF", "globalRank": 1044, "totalPlayer": 1731}, {"date": "2021-03-09", "server": 13, "serverRank": 27, "globalRank": 795, "totalPlayer": 1707}, {"date": "2021-03-10", "server": 14, "serverRank": 54, "globalRank": 886, "totalPlayer": 1581}, {"date": "2021-03-11", "server": 16, "serverRank": 40, "globalRank": 1000, "totalPlayer": 1705}, {"date": "2021-03-12", "server": 16, "serverRank": 16, "globalRank": 976, "totalPlayer": 1443}, {"date": "2021-03-13", "server": 8, "serverRank": 8, "globalRank": 456, "totalPlayer": 1220}, {"date": "2021-03-14", "server": 9, "serverRank": 48, "globalRank": 560, "totalPlayer": 1308}, {"date": "2021-03-16", "server": 15, "serverRank": 24, "globalRank": 920, "totalPlayer": 1644}, {"date": "2021-03-17", "server": 14, "serverRank": 11, "globalRank": 843, "totalPlayer": 1683}, {"date": "2021-03-18", "server": 10, "serverRank": 7, "globalRank": 583, "totalPlayer": 1683}]}}