{"playerID": "34932f93-7fdc-42b0-90a5-95dd1d25742e", "playerNames": [{"playerName": "WillemTM", "sinceDate": "2021-02-09"}], "results": {"cotd": [{"date": "2021-01-02", "server": 4, "serverRank": 17, "globalRank": 209, "totalPlayer": 1152}, {"date": "2021-01-20", "server": 2, "serverRank": 50, "globalRank": 114, "totalPlayer": 1432}, {"date": "2021-01-26", "server": 6, "serverRank": "DNF", "globalRank": 378, "totalPlayer": 1525}, {"date": "2021-01-30", "server": 5, "serverRank": "DNF", "globalRank": 272, "totalPlayer": 971}, {"date": "2021-01-31", "server": 6, "serverRank": 17, "globalRank": 337, "totalPlayer": 1440}, {"date": "2021-02-05", "server": 2, "serverRank": "DNF", "globalRank": 124, "totalPlayer": 1371}, {"date": "2021-02-09", "server": 6, "serverRank": 48, "globalRank": 368, "totalPlayer": 1395}, {"date": "2021-02-11", "server": 4, "serverRank": 58, "globalRank": 250, "totalPlayer": 1448}, {"date": "2021-02-12", "server": 18, "serverRank": "DNF", "globalRank": 1145, "totalPlayer": 1376}, {"date": "2021-04-29", "server": 4, "serverRank": 52, "globalRank": 244, "totalPlayer": 2424}]}}