{"playerID": "3581a45a-a105-4f4c-b89a-1f77525418c3", "playerNames": [{"playerName": "TengennToppa", "sinceDate": "2021-02-09"}], "results": {"cotd": [{"date": "2020-11-26", "server": 14, "serverRank": 37, "globalRank": 869, "totalPlayer": 1512}, {"date": "2020-11-27", "server": 13, "serverRank": 4, "globalRank": 772, "totalPlayer": 1525}, {"date": "2020-11-30", "server": 18, "serverRank": 22, "globalRank": 1110, "totalPlayer": 1683}, {"date": "2020-12-11", "server": 22, "serverRank": 5, "globalRank": 1349, "totalPlayer": 1407}, {"date": "2020-12-12", "server": 12, "serverRank": 25, "globalRank": 729, "totalPlayer": 1255}, {"date": "2020-12-14", "server": 20, "serverRank": 20, "globalRank": 1236, "totalPlayer": 1502}, {"date": "2020-12-16", "server": 12, "serverRank": 19, "globalRank": 723, "totalPlayer": 1480}, {"date": "2021-01-21", "server": 12, "serverRank": 33, "globalRank": 737, "totalPlayer": 1417}, {"date": "2021-01-29", "server": 14, "serverRank": "DNF", "globalRank": 842, "totalPlayer": 1347}, {"date": "2021-01-30", "server": 13, "serverRank": "DNF", "globalRank": 779, "totalPlayer": 971}, {"date": "2021-02-05", "server": 9, "serverRank": 35, "globalRank": 547, "totalPlayer": 1371}]}}