{"playerID": "36a373e1-c7d6-4987-8ec5-9d12c985b9bc", "playerNames": [{"playerName": "Scintillo", "sinceDate": "2021-02-09"}], "results": {"cotd": [{"date": "2021-01-30", "server": 13, "serverRank": "DNF", "globalRank": 778, "totalPlayer": 971}, {"date": "2021-02-01", "server": 22, "serverRank": "DNF", "globalRank": 1405, "totalPlayer": 1500}, {"date": "2021-02-04", "server": 21, "serverRank": "DNF", "globalRank": 1299, "totalPlayer": 1424}, {"date": "2021-02-09", "server": 20, "serverRank": 47, "globalRank": 1263, "totalPlayer": 1395}, {"date": "2021-02-10", "server": 22, "serverRank": 32, "globalRank": 1376, "totalPlayer": 1523}]}}