{"playerID": "41f338a9-9046-4655-836c-6f68718924b0", "playerNames": [{"playerName": "Julian_TM", "sinceDate": "2021-02-09"}], "results": {"cotd": [{"date": "2020-11-19", "server": 5, "serverRank": 49, "globalRank": 305, "totalPlayer": 1624}, {"date": "2020-11-20", "server": 6, "serverRank": 11, "globalRank": 331, "totalPlayer": 1655}, {"date": "2020-11-22", "server": 7, "serverRank": 17, "globalRank": 401, "totalPlayer": 1551}, {"date": "2020-11-25", "server": 10, "serverRank": 37, "globalRank": 613, "totalPlayer": 1604}, {"date": "2020-11-26", "server": 5, "serverRank": 5, "globalRank": 261, "totalPlayer": 1512}, {"date": "2020-11-27", "server": 5, "serverRank": 54, "globalRank": 310, "totalPlayer": 1525}, {"date": "2021-02-06", "server": 6, "serverRank": "DNF", "globalRank": 381, "totalPlayer": 1080}, {"date": "2021-04-13", "server": 6, "serverRank": 41, "globalRank": 361, "totalPlayer": 2119}, {"date": "2021-05-04", "server": 6, "serverRank": 19, "globalRank": 339, "totalPlayer": 2656}]}}