{"playerID": "4668e631-41db-42ec-8986-d464142ba9b4", "playerNames": [{"playerName": "Kuyiyterea", "sinceDate": "2021-02-09"}], "results": {"cotd": [{"date": "2020-11-04", "server": 7, "serverRank": 10, "globalRank": 394, "totalPlayer": 1058}, {"date": "2021-01-18", "server": 9, "serverRank": 28, "globalRank": 540, "totalPlayer": 1439}, {"date": "2021-02-07", "server": 18, "serverRank": 2, "globalRank": 1090, "totalPlayer": 1374}, {"date": "2021-02-09", "server": 13, "serverRank": 46, "globalRank": 814, "totalPlayer": 1395}]}}