{"playerID": "56db4e49-0631-4b99-82aa-414cf2b05816", "playerNames": [{"playerName": "Riiskyy", "sinceDate": "2021-04-13"}], "results": {"cotd": [{"date": "2021-04-13", "server": 21, "serverRank": 26, "globalRank": 1306, "totalPlayer": 2119}, {"date": "2021-04-24", "server": 10, "serverRank": 44, "globalRank": 620, "totalPlayer": 1954}, {"date": "2021-04-25", "server": 5, "serverRank": 45, "globalRank": 301, "totalPlayer": 2275}, {"date": "2021-04-26", "server": 15, "serverRank": "DNF", "globalRank": 944, "totalPlayer": 2532}, {"date": "2021-04-27", "server": 10, "serverRank": 34, "globalRank": 610, "totalPlayer": 2462}, {"date": "2021-04-28", "server": 7, "serverRank": 21, "globalRank": 405, "totalPlayer": 2341}, {"date": "2021-04-29", "server": 14, "serverRank": 28, "globalRank": 860, "totalPlayer": 2424}, {"date": "2021-04-30", "server": 18, "serverRank": 13, "globalRank": 1101, "totalPlayer": 2209}]}}