{"playerID": "56e17ba5-9e3e-4513-a472-2e16aff4499e", "playerNames": [{"playerName": "Ionic_Andrew", "sinceDate": "2021-02-09"}], "results": {"cotd": [{"date": "2020-12-25", "server": 11, "serverRank": 34, "globalRank": 674, "totalPlayer": 838}, {"date": "2020-12-26", "server": 16, "serverRank": 27, "globalRank": 987, "totalPlayer": 1061}, {"date": "2020-12-27", "server": 17, "serverRank": 55, "globalRank": 1079, "totalPlayer": 1215}, {"date": "2020-12-30", "server": 18, "serverRank": 28, "globalRank": 1116, "totalPlayer": 1240}, {"date": "2021-01-05", "server": 20, "serverRank": 45, "globalRank": 1261, "totalPlayer": 1353}]}}