{"playerID": "57ec4191-3eed-4b87-ad33-eb038909a9dd", "playerNames": [{"playerName": "Purge.Billouz", "sinceDate": "2021-02-09"}], "results": {"cotd": [{"date": "2020-11-18", "server": 2, "serverRank": "DNF", "globalRank": 125, "totalPlayer": 1684}, {"date": "2020-11-19", "server": 7, "serverRank": 14, "globalRank": 398, "totalPlayer": 1624}, {"date": "2020-11-20", "server": 1, "serverRank": 20, "globalRank": 20, "totalPlayer": 1655}, {"date": "2020-11-23", "server": 2, "serverRank": 9, "globalRank": 73, "totalPlayer": 1696}, {"date": "2020-11-24", "server": 8, "serverRank": 23, "globalRank": 471, "totalPlayer": 1594}, {"date": "2020-11-25", "server": 1, "serverRank": 53, "globalRank": 53, "totalPlayer": 1604}, {"date": "2020-11-26", "server": 2, "serverRank": 23, "globalRank": 87, "totalPlayer": 1512}, {"date": "2020-11-30", "server": 1, "serverRank": 19, "globalRank": 19, "totalPlayer": 1683}, {"date": "2020-12-01", "server": 2, "serverRank": 15, "globalRank": 79, "totalPlayer": 1522}, {"date": "2020-12-02", "server": 3, "serverRank": 1, "globalRank": 129, "totalPlayer": 1536}, {"date": "2020-12-03", "server": 1, "serverRank": 6, "globalRank": 6, "totalPlayer": 1507}, {"date": "2020-12-04", "server": 1, "serverRank": 3, "globalRank": 3, "totalPlayer": 1461}, {"date": "2020-12-06", "server": 1, "serverRank": 13, "globalRank": 13, "totalPlayer": 1298}, {"date": "2020-12-07", "server": 1, "serverRank": 57, "globalRank": 57, "totalPlayer": 1595}, {"date": "2020-12-08", "server": 2, "serverRank": 2, "globalRank": 66, "totalPlayer": 1599}, {"date": "2020-12-09", "server": 3, "serverRank": 43, "globalRank": 171, "totalPlayer": 1462}, {"date": "2020-12-17", "server": 1, "serverRank": 40, "globalRank": 40, "totalPlayer": 1515}, {"date": "2020-12-20", "server": 1, "serverRank": 26, "globalRank": 26, "totalPlayer": 1267}, {"date": "2020-12-21", "server": 1, "serverRank": 14, "globalRank": 14, "totalPlayer": 1429}, {"date": "2020-12-22", "server": 1, "serverRank": 39, "globalRank": 39, "totalPlayer": 1403}, {"date": "2020-12-23", "server": 1, "serverRank": 52, "globalRank": 52, "totalPlayer": 1225}, {"date": "2020-12-26", "server": 7, "serverRank": "DNF", "globalRank": 448, "totalPlayer": 1061}, {"date": "2021-01-05", "server": 3, "serverRank": 43, "globalRank": 171, "totalPlayer": 1353}, {"date": "2021-01-06", "server": 1, "serverRank": 6, "globalRank": 6, "totalPlayer": 1331}, {"date": "2021-01-08", "server": 1, "serverRank": 35, "globalRank": 35, "totalPlayer": 1150}, {"date": "2021-01-10", "server": 1, "serverRank": 48, "globalRank": 48, "totalPlayer": 1357}, {"date": "2021-01-12", "server": 3, "serverRank": 18, "globalRank": 146, "totalPlayer": 1353}, {"date": "2021-01-13", "server": 1, "serverRank": 55, "globalRank": 55, "totalPlayer": 1380}, {"date": "2021-01-14", "server": 2, "serverRank": 42, "globalRank": 106, "totalPlayer": 1388}, {"date": "2021-02-05", "server": 4, "serverRank": "DNF", "globalRank": 247, "totalPlayer": 1371}, {"date": "2021-02-18", "server": 11, "serverRank": 3, "globalRank": 643, "totalPlayer": 1532}]}}