{"playerID": "623923d3-8f6f-4c11-9f7b-c7f5c319ad52", "playerNames": [{"playerName": "UnreconstructdM", "sinceDate": "2021-03-02"}], "results": {"cotd": [{"date": "2021-03-02", "server": 19, "serverRank": 6, "globalRank": 1158, "totalPlayer": 1689}, {"date": "2021-03-03", "server": 20, "serverRank": 16, "globalRank": 1232, "totalPlayer": 1617}, {"date": "2021-03-04", "server": 19, "serverRank": 11, "globalRank": 1163, "totalPlayer": 1705}, {"date": "2021-03-05", "server": 14, "serverRank": 56, "globalRank": 888, "totalPlayer": 1612}]}}