{"playerID": "643731e7-2140-4f31-9bf6-2c47b9c7f829", "playerNames": [{"playerName": "GoorGel", "sinceDate": "2021-03-11"}], "results": {"cotd": [{"date": "2021-03-11", "server": 10, "serverRank": 38, "globalRank": 614, "totalPlayer": 1705}, {"date": "2021-03-15", "server": 18, "serverRank": 1, "globalRank": 1089, "totalPlayer": 1706}, {"date": "2021-03-16", "server": 17, "serverRank": 54, "globalRank": 1078, "totalPlayer": 1644}, {"date": "2021-03-17", "server": 12, "serverRank": 27, "globalRank": 731, "totalPlayer": 1683}]}}