{"playerID": "763ca55c-9edd-4535-ab4e-954e647e751a", "playerNames": [{"playerName": "Eclipsoon", "sinceDate": "2021-02-09"}], "results": {"cotd": [{"date": "2020-11-04", "server": 9, "serverRank": 28, "globalRank": 540, "totalPlayer": 1058}, {"date": "2020-11-12", "server": 16, "serverRank": 29, "globalRank": 989, "totalPlayer": 1400}, {"date": "2020-11-27", "server": 23, "serverRank": 32, "globalRank": 1440, "totalPlayer": 1525}, {"date": "2021-03-17", "server": 7, "serverRank": 52, "globalRank": 436, "totalPlayer": 1683}, {"date": "2021-03-18", "server": 14, "serverRank": 12, "globalRank": 844, "totalPlayer": 1683}]}}