{"playerID": "78d62e5e-e738-48a3-b58b-de7af30cd6a4", "playerNames": [{"playerName": "StumpyThePirate", "sinceDate": "2021-02-09"}], "results": {"cotd": [{"date": "2020-11-02", "server": 6, "serverRank": "DNF", "globalRank": 325, "totalPlayer": 671}, {"date": "2020-11-03", "server": 9, "serverRank": 43, "globalRank": 555, "totalPlayer": 864}, {"date": "2020-11-10", "server": 11, "serverRank": 47, "globalRank": 687, "totalPlayer": 1312}, {"date": "2020-11-23", "server": 11, "serverRank": 56, "globalRank": 696, "totalPlayer": 1696}]}}