{"playerID": "7b5447fc-152b-44d0-8e93-523e90e037c2", "playerNames": [{"playerName": "Nemonal", "sinceDate": "2021-03-13"}], "results": {"cotd": [{"date": "2021-03-13", "server": 14, "serverRank": 20, "globalRank": 852, "totalPlayer": 1220}, {"date": "2021-03-23", "server": 19, "serverRank": 13, "globalRank": 1165, "totalPlayer": 1765}, {"date": "2021-03-24", "server": 17, "serverRank": 8, "globalRank": 1032, "totalPlayer": 1806}, {"date": "2021-03-25", "server": 13, "serverRank": 33, "globalRank": 801, "totalPlayer": 1766}, {"date": "2021-03-26", "server": 14, "serverRank": 6, "globalRank": 838, "totalPlayer": 1600}, {"date": "2021-03-28", "server": 9, "serverRank": 3, "globalRank": 515, "totalPlayer": 1517}, {"date": "2021-03-29", "server": 16, "serverRank": 4, "globalRank": 964, "totalPlayer": 1676}]}}