{"playerID": "80479296-8c8e-4f57-8846-e1ffc603eede", "playerNames": [{"playerName": "the.sad.gamer", "sinceDate": "2021-02-09"}], "results": {"cotd": [{"date": "2021-02-08", "server": 21, "serverRank": 51, "globalRank": 1331, "totalPlayer": 1533}, {"date": "2021-02-10", "server": 23, "serverRank": 37, "globalRank": 1445, "totalPlayer": 1523}, {"date": "2021-02-11", "server": 22, "serverRank": 34, "globalRank": 1378, "totalPlayer": 1448}, {"date": "2021-02-12", "server": 19, "serverRank": 29, "globalRank": 1181, "totalPlayer": 1376}, {"date": "2021-02-14", "server": 20, "serverRank": 29, "globalRank": 1245, "totalPlayer": 1299}, {"date": "2021-02-18", "server": 21, "serverRank": 3, "globalRank": 1283, "totalPlayer": 1532}, {"date": "2021-02-19", "server": 21, "serverRank": 14, "globalRank": 1294, "totalPlayer": 1379}, {"date": "2021-02-20", "server": 12, "serverRank": 49, "globalRank": 753, "totalPlayer": 1038}, {"date": "2021-02-21", "server": 16, "serverRank": "DNF", "globalRank": 965, "totalPlayer": 1024}, {"date": "2021-02-23", "server": 20, "serverRank": 37, "globalRank": 1253, "totalPlayer": 1469}]}}