{"playerID": "824ac9dc-07b6-442a-a6d9-971add2f59a0", "playerNames": [{"playerName": "Kaptn_Simon", "sinceDate": "2021-03-02"}], "results": {"cotd": [{"date": "2021-03-02", "server": 18, "serverRank": 57, "globalRank": 1145, "totalPlayer": 1689}, {"date": "2021-03-07", "server": 22, "serverRank": "DNF", "globalRank": 1408, "totalPlayer": 1680}, {"date": "2021-03-08", "server": 17, "serverRank": "DNF", "globalRank": 1084, "totalPlayer": 1731}, {"date": "2021-03-09", "server": 23, "serverRank": "DNF", "globalRank": 1465, "totalPlayer": 1707}]}}