{"playerID": "8437dbfc-2027-4d93-9a68-7fe741a72e26", "playerNames": [{"playerName": "pferdmin", "sinceDate": "2021-02-09"}], "results": {"cotd": [{"date": "2021-02-06", "server": 12, "serverRank": 31, "globalRank": 735, "totalPlayer": 1080}, {"date": "2021-02-10", "server": 23, "serverRank": 4, "globalRank": 1412, "totalPlayer": 1523}, {"date": "2021-02-11", "server": 15, "serverRank": 47, "globalRank": 943, "totalPlayer": 1448}, {"date": "2021-02-12", "server": 13, "serverRank": "DNF", "globalRank": 830, "totalPlayer": 1376}, {"date": "2021-02-13", "server": 8, "serverRank": 32, "globalRank": 480, "totalPlayer": 1092}, {"date": "2021-02-18", "server": 11, "serverRank": 15, "globalRank": 655, "totalPlayer": 1532}, {"date": "2021-02-25", "server": 20, "serverRank": 8, "globalRank": 1224, "totalPlayer": 1491}, {"date": "2021-02-28", "server": 12, "serverRank": 43, "globalRank": 747, "totalPlayer": 1418}, {"date": "2021-03-01", "server": 12, "serverRank": 7, "globalRank": 711, "totalPlayer": 1607}, {"date": "2021-03-02", "server": 21, "serverRank": 3, "globalRank": 1283, "totalPlayer": 1689}, {"date": "2021-03-04", "server": 20, "serverRank": 32, "globalRank": 1248, "totalPlayer": 1705}, {"date": "2021-03-06", "server": 19, "serverRank": "DNF", "globalRank": 1214, "totalPlayer": 1307}, {"date": "2021-03-11", "server": 14, "serverRank": "DNF", "globalRank": 891, "totalPlayer": 1705}, {"date": "2021-03-14", "server": 16, "serverRank": 55, "globalRank": 1015, "totalPlayer": 1308}]}}