{"playerID": "8a33bee9-6971-41b7-8e64-ef07f9952ddb", "playerNames": [{"playerName": "vr-Julien36", "sinceDate": "2021-02-09"}], "results": {"cotd": [{"date": "2020-12-07", "server": 5, "serverRank": 1, "globalRank": 257, "totalPlayer": 1595}, {"date": "2020-12-27", "server": 5, "serverRank": 19, "globalRank": 275, "totalPlayer": 1215}, {"date": "2021-01-02", "server": 3, "serverRank": 26, "globalRank": 154, "totalPlayer": 1152}, {"date": "2021-01-03", "server": 2, "serverRank": 23, "globalRank": 87, "totalPlayer": 1285}, {"date": "2021-01-04", "server": 4, "serverRank": 22, "globalRank": 214, "totalPlayer": 1349}, {"date": "2021-01-06", "server": 2, "serverRank": 31, "globalRank": 95, "totalPlayer": 1331}, {"date": "2021-01-11", "server": 3, "serverRank": 7, "globalRank": 135, "totalPlayer": 1391}, {"date": "2021-01-14", "server": 2, "serverRank": 30, "globalRank": 94, "totalPlayer": 1388}, {"date": "2021-01-17", "server": 6, "serverRank": 32, "globalRank": 352, "totalPlayer": 1315}, {"date": "2021-01-18", "server": 3, "serverRank": 29, "globalRank": 157, "totalPlayer": 1439}, {"date": "2021-01-19", "server": 15, "serverRank": "DNF", "globalRank": 957, "totalPlayer": 1413}, {"date": "2021-01-25", "server": 2, "serverRank": 44, "globalRank": 108, "totalPlayer": 1504}, {"date": "2021-01-28", "server": 1, "serverRank": "DNF", "globalRank": 5, "totalPlayer": 1538}, {"date": "2021-01-31", "server": 3, "serverRank": 7, "globalRank": 135, "totalPlayer": 1440}, {"date": "2021-02-25", "server": 4, "serverRank": 48, "globalRank": 240, "totalPlayer": 1491}, {"date": "2021-03-27", "server": 3, "serverRank": 7, "globalRank": 135, "totalPlayer": 1582}, {"date": "2021-03-29", "server": 3, "serverRank": 39, "globalRank": 167, "totalPlayer": 1676}, {"date": "2021-04-04", "server": 16, "serverRank": 42, "globalRank": 1002, "totalPlayer": 1491}, {"date": "2021-04-08", "server": 5, "serverRank": 41, "globalRank": 297, "totalPlayer": 2019}, {"date": "2021-04-09", "server": 2, "serverRank": 7, "globalRank": 71, "totalPlayer": 1825}, {"date": "2021-04-11", "server": 21, "serverRank": 36, "globalRank": 1316, "totalPlayer": 1985}, {"date": "2021-04-12", "server": 3, "serverRank": 36, "globalRank": 164, "totalPlayer": 2155}, {"date": "2021-04-13", "server": 2, "serverRank": 46, "globalRank": 110, "totalPlayer": 2119}, {"date": "2021-04-14", "server": 3, "serverRank": 27, "globalRank": 155, "totalPlayer": 2178}, {"date": "2021-04-17", "server": 2, "serverRank": 37, "globalRank": 101, "totalPlayer": 1761}]}}