{"playerID": "8c051d6e-d0b5-4553-b5d9-848205f4f4a3", "playerNames": [{"playerName": "VawerLine", "sinceDate": "2021-03-05"}], "results": {"cotd": [{"date": "2021-03-05", "server": 17, "serverRank": 43, "globalRank": 1067, "totalPlayer": 1612}, {"date": "2021-03-11", "server": 20, "serverRank": 13, "globalRank": 1229, "totalPlayer": 1705}, {"date": "2021-03-16", "server": 14, "serverRank": "DNF", "globalRank": 894, "totalPlayer": 1644}, {"date": "2021-03-23", "server": 21, "serverRank": 13, "globalRank": 1293, "totalPlayer": 1765}]}}