{"playerID": "9d7e69e5-7aa3-4340-b66c-741c6c103a63", "playerNames": [{"playerName": "PlexCH", "sinceDate": "2021-02-09"}], "results": {"cotd": [{"date": "2020-11-20", "server": 13, "serverRank": 18, "globalRank": 786, "totalPlayer": 1655}, {"date": "2020-11-22", "server": 11, "serverRank": 50, "globalRank": 690, "totalPlayer": 1551}, {"date": "2020-11-23", "server": 18, "serverRank": 9, "globalRank": 1097, "totalPlayer": 1696}, {"date": "2020-11-24", "server": 17, "serverRank": 53, "globalRank": 1077, "totalPlayer": 1594}, {"date": "2020-11-26", "server": 11, "serverRank": 8, "globalRank": 648, "totalPlayer": 1512}, {"date": "2020-11-27", "server": 18, "serverRank": 29, "globalRank": 1117, "totalPlayer": 1525}, {"date": "2020-11-28", "server": 12, "serverRank": 47, "globalRank": 751, "totalPlayer": 1364}, {"date": "2020-11-29", "server": 10, "serverRank": 4, "globalRank": 580, "totalPlayer": 1466}, {"date": "2020-11-30", "server": 15, "serverRank": 48, "globalRank": 944, "totalPlayer": 1683}, {"date": "2020-12-01", "server": 16, "serverRank": 46, "globalRank": 1006, "totalPlayer": 1522}, {"date": "2020-12-02", "server": 12, "serverRank": 34, "globalRank": 738, "totalPlayer": 1536}, {"date": "2020-12-03", "server": 12, "serverRank": 25, "globalRank": 729, "totalPlayer": 1507}, {"date": "2020-12-05", "server": 11, "serverRank": 27, "globalRank": 667, "totalPlayer": 1322}, {"date": "2020-12-06", "server": 8, "serverRank": 46, "globalRank": 494, "totalPlayer": 1298}, {"date": "2020-12-07", "server": 13, "serverRank": 47, "globalRank": 815, "totalPlayer": 1595}, {"date": "2020-12-08", "server": 11, "serverRank": 30, "globalRank": 670, "totalPlayer": 1599}, {"date": "2020-12-09", "server": 18, "serverRank": 4, "globalRank": 1092, "totalPlayer": 1462}, {"date": "2020-12-12", "server": 11, "serverRank": 5, "globalRank": 645, "totalPlayer": 1255}, {"date": "2020-12-13", "server": 12, "serverRank": 8, "globalRank": 712, "totalPlayer": 1438}, {"date": "2020-12-14", "server": 12, "serverRank": 10, "globalRank": 714, "totalPlayer": 1502}, {"date": "2020-12-15", "server": 9, "serverRank": 38, "globalRank": 550, "totalPlayer": 1496}, {"date": "2020-12-16", "server": 11, "serverRank": 23, "globalRank": 663, "totalPlayer": 1480}, {"date": "2020-12-17", "server": 13, "serverRank": 50, "globalRank": 818, "totalPlayer": 1515}, {"date": "2020-12-18", "server": 11, "serverRank": 3, "globalRank": 643, "totalPlayer": 1404}, {"date": "2020-12-20", "server": 12, "serverRank": 33, "globalRank": 737, "totalPlayer": 1267}, {"date": "2020-12-22", "server": 6, "serverRank": 33, "globalRank": 353, "totalPlayer": 1403}, {"date": "2020-12-23", "server": 11, "serverRank": 16, "globalRank": 656, "totalPlayer": 1225}, {"date": "2020-12-24", "server": 6, "serverRank": 20, "globalRank": 340, "totalPlayer": 554}, {"date": "2020-12-25", "server": 4, "serverRank": 27, "globalRank": 219, "totalPlayer": 838}, {"date": "2020-12-26", "server": 7, "serverRank": 55, "globalRank": 439, "totalPlayer": 1061}, {"date": "2020-12-27", "server": 6, "serverRank": 21, "globalRank": 341, "totalPlayer": 1215}, {"date": "2020-12-29", "server": 7, "serverRank": 6, "globalRank": 390, "totalPlayer": 1318}, {"date": "2020-12-30", "server": 12, "serverRank": 9, "globalRank": 713, "totalPlayer": 1240}, {"date": "2020-12-31", "server": 3, "serverRank": 13, "globalRank": 141, "totalPlayer": 727}, {"date": "2021-01-01", "server": 7, "serverRank": 8, "globalRank": 392, "totalPlayer": 1135}, {"date": "2021-01-03", "server": 15, "serverRank": 1, "globalRank": 897, "totalPlayer": 1285}, {"date": "2021-01-04", "server": 11, "serverRank": "DNF", "globalRank": 669, "totalPlayer": 1349}, {"date": "2021-01-05", "server": 12, "serverRank": 15, "globalRank": 719, "totalPlayer": 1353}, {"date": "2021-01-07", "server": 6, "serverRank": 53, "globalRank": 373, "totalPlayer": 1401}, {"date": "2021-01-08", "server": 12, "serverRank": 4, "globalRank": 708, "totalPlayer": 1150}, {"date": "2021-01-10", "server": 10, "serverRank": 3, "globalRank": 579, "totalPlayer": 1357}, {"date": "2021-01-11", "server": 15, "serverRank": 2, "globalRank": 898, "totalPlayer": 1391}, {"date": "2021-01-13", "server": 10, "serverRank": 9, "globalRank": 585, "totalPlayer": 1380}, {"date": "2021-01-14", "server": 15, "serverRank": 12, "globalRank": 908, "totalPlayer": 1388}, {"date": "2021-01-15", "server": 10, "serverRank": 32, "globalRank": 608, "totalPlayer": 1286}, {"date": "2021-01-16", "server": 9, "serverRank": 30, "globalRank": 542, "totalPlayer": 1178}, {"date": "2021-01-17", "server": 10, "serverRank": 15, "globalRank": 591, "totalPlayer": 1315}, {"date": "2021-01-18", "server": 12, "serverRank": 11, "globalRank": 715, "totalPlayer": 1439}, {"date": "2021-01-19", "server": 15, "serverRank": 43, "globalRank": 939, "totalPlayer": 1413}, {"date": "2021-01-20", "server": 10, "serverRank": 55, "globalRank": 631, "totalPlayer": 1432}, {"date": "2021-01-21", "server": 9, "serverRank": 41, "globalRank": 553, "totalPlayer": 1417}, {"date": "2021-01-22", "server": 12, "serverRank": 17, "globalRank": 721, "totalPlayer": 1424}, {"date": "2021-01-25", "server": 10, "serverRank": 23, "globalRank": 599, "totalPlayer": 1504}, {"date": "2021-01-26", "server": 10, "serverRank": 35, "globalRank": 611, "totalPlayer": 1525}, {"date": "2021-02-01", "server": 13, "serverRank": 50, "globalRank": 818, "totalPlayer": 1500}, {"date": "2021-02-03", "server": 7, "serverRank": 48, "globalRank": 432, "totalPlayer": 1229}, {"date": "2021-02-05", "server": 9, "serverRank": 23, "globalRank": 535, "totalPlayer": 1371}, {"date": "2021-02-07", "server": 6, "serverRank": 11, "globalRank": 331, "totalPlayer": 1374}, {"date": "2021-02-08", "server": 13, "serverRank": 9, "globalRank": 777, "totalPlayer": 1533}, {"date": "2021-02-11", "server": 8, "serverRank": 5, "globalRank": 453, "totalPlayer": 1448}, {"date": "2021-02-12", "server": 8, "serverRank": 47, "globalRank": 495, "totalPlayer": 1376}, {"date": "2021-02-13", "server": 8, "serverRank": 8, "globalRank": 456, "totalPlayer": 1092}, {"date": "2021-02-14", "server": 8, "serverRank": 18, "globalRank": 466, "totalPlayer": 1299}, {"date": "2021-02-15", "server": 13, "serverRank": 3, "globalRank": 771, "totalPlayer": 1519}, {"date": "2021-02-16", "server": 10, "serverRank": 2, "globalRank": 578, "totalPlayer": 1542}, {"date": "2021-02-18", "server": 9, "serverRank": 9, "globalRank": 521, "totalPlayer": 1532}, {"date": "2021-02-19", "server": 7, "serverRank": 43, "globalRank": 427, "totalPlayer": 1379}, {"date": "2021-02-20", "server": 7, "serverRank": 36, "globalRank": 420, "totalPlayer": 1038}, {"date": "2021-02-22", "server": 10, "serverRank": 26, "globalRank": 602, "totalPlayer": 1497}, {"date": "2021-02-23", "server": 12, "serverRank": 55, "globalRank": 759, "totalPlayer": 1469}, {"date": "2021-02-24", "server": 8, "serverRank": 5, "globalRank": 453, "totalPlayer": 1437}, {"date": "2021-02-25", "server": 12, "serverRank": 39, "globalRank": 743, "totalPlayer": 1491}, {"date": "2021-02-26", "server": 11, "serverRank": 3, "globalRank": 643, "totalPlayer": 1408}, {"date": "2021-02-27", "server": 5, "serverRank": 37, "globalRank": 293, "totalPlayer": 1111}, {"date": "2021-02-28", "server": 11, "serverRank": 24, "globalRank": 664, "totalPlayer": 1418}, {"date": "2021-03-01", "server": 5, "serverRank": 21, "globalRank": 277, "totalPlayer": 1607}, {"date": "2021-03-05", "server": 10, "serverRank": 37, "globalRank": 613, "totalPlayer": 1612}, {"date": "2021-03-06", "server": 7, "serverRank": 47, "globalRank": 431, "totalPlayer": 1307}, {"date": "2021-03-09", "server": 10, "serverRank": 5, "globalRank": 581, "totalPlayer": 1707}, {"date": "2021-03-10", "server": 10, "serverRank": 17, "globalRank": 593, "totalPlayer": 1581}, {"date": "2021-03-15", "server": 12, "serverRank": 6, "globalRank": 710, "totalPlayer": 1706}, {"date": "2021-03-16", "server": 8, "serverRank": 8, "globalRank": 456, "totalPlayer": 1644}, {"date": "2021-03-17", "server": 11, "serverRank": 15, "globalRank": 655, "totalPlayer": 1683}, {"date": "2021-03-18", "server": 15, "serverRank": 3, "globalRank": 899, "totalPlayer": 1683}, {"date": "2021-03-19", "server": 11, "serverRank": 11, "globalRank": 651, "totalPlayer": 1595}, {"date": "2021-03-22", "server": 11, "serverRank": 18, "globalRank": 658, "totalPlayer": 1748}, {"date": "2021-03-23", "server": 9, "serverRank": 45, "globalRank": 557, "totalPlayer": 1765}]}}