{"playerID": "a4a341cc-64ed-43db-a167-c7fdb172bdb1", "playerNames": [{"playerName": "Musophyle", "sinceDate": "2021-02-09"}], "results": {"cotd": [{"date": "2020-11-11", "server": 17, "serverRank": 23, "globalRank": 1047, "totalPlayer": 1413}, {"date": "2020-11-12", "server": 15, "serverRank": 43, "globalRank": 939, "totalPlayer": 1400}, {"date": "2020-11-13", "server": 17, "serverRank": 46, "globalRank": 1070, "totalPlayer": 1420}, {"date": "2020-11-15", "server": 9, "serverRank": 7, "globalRank": 519, "totalPlayer": 1150}]}}