{"playerID": "ca6f968a-c0d8-4f3a-9509-7150bf170b25", "playerNames": [{"playerName": "Giffyy.", "sinceDate": "2021-02-09"}], "results": {"cotd": [{"date": "2020-11-14", "server": 2, "serverRank": 60, "globalRank": 124, "totalPlayer": 1242}, {"date": "2020-11-15", "server": 3, "serverRank": 11, "globalRank": 139, "totalPlayer": 1150}, {"date": "2020-11-18", "server": 8, "serverRank": 50, "globalRank": 498, "totalPlayer": 1684}, {"date": "2020-11-20", "server": 14, "serverRank": 38, "globalRank": 870, "totalPlayer": 1655}, {"date": "2020-11-23", "server": 7, "serverRank": 41, "globalRank": 425, "totalPlayer": 1696}]}}