{"playerID": "d5e679c7-fb41-420c-b6ed-566808622391", "playerNames": [{"playerName": "SkySoSalty", "sinceDate": "2021-02-09"}], "results": {"cotd": [{"date": "2020-11-05", "server": 16, "serverRank": 3, "globalRank": 963, "totalPlayer": 1218}, {"date": "2020-11-13", "server": 18, "serverRank": 38, "globalRank": 1126, "totalPlayer": 1420}, {"date": "2020-11-20", "server": 15, "serverRank": 45, "globalRank": 941, "totalPlayer": 1655}, {"date": "2020-11-25", "server": 16, "serverRank": 39, "globalRank": 999, "totalPlayer": 1604}, {"date": "2021-02-08", "server": 20, "serverRank": 48, "globalRank": 1264, "totalPlayer": 1533}]}}