{"playerID": "d75d3ddf-b2e8-4905-9943-993f344c92e3", "playerNames": [{"playerName": "kenkaro-Py", "sinceDate": "2021-03-02"}], "results": {"cotd": [{"date": "2021-03-02", "server": 23, "serverRank": 7, "globalRank": 1415, "totalPlayer": 1689}, {"date": "2021-03-03", "server": 17, "serverRank": 9, "globalRank": 1033, "totalPlayer": 1617}, {"date": "2021-03-04", "server": 16, "serverRank": 9, "globalRank": 969, "totalPlayer": 1705}, {"date": "2021-03-05", "server": 19, "serverRank": 22, "globalRank": 1174, "totalPlayer": 1612}, {"date": "2021-03-07", "server": 21, "serverRank": 27, "globalRank": 1307, "totalPlayer": 1680}, {"date": "2021-03-09", "server": 22, "serverRank": 24, "globalRank": 1368, "totalPlayer": 1707}, {"date": "2021-03-10", "server": 10, "serverRank": 52, "globalRank": 628, "totalPlayer": 1581}]}}