{"playerID": "dd22a321-d7a8-4ab4-b61e-508e64b242fc", "playerNames": [{"playerName": "Clumsea", "sinceDate": "2021-02-09"}], "results": {"cotd": [{"date": "2020-11-11", "server": 17, "serverRank": 57, "globalRank": 1081, "totalPlayer": 1413}, {"date": "2020-11-12", "server": 8, "serverRank": 15, "globalRank": 463, "totalPlayer": 1400}, {"date": "2020-11-13", "server": 11, "serverRank": 52, "globalRank": 692, "totalPlayer": 1420}, {"date": "2020-11-21", "server": 9, "serverRank": 18, "globalRank": 530, "totalPlayer": 1470}, {"date": "2020-11-22", "server": 7, "serverRank": 28, "globalRank": 412, "totalPlayer": 1551}, {"date": "2020-11-23", "server": 7, "serverRank": 8, "globalRank": 392, "totalPlayer": 1696}, {"date": "2020-11-28", "server": 9, "serverRank": 12, "globalRank": 524, "totalPlayer": 1364}, {"date": "2020-11-29", "server": 13, "serverRank": 38, "globalRank": 806, "totalPlayer": 1466}, {"date": "2020-12-14", "server": 11, "serverRank": 44, "globalRank": 684, "totalPlayer": 1502}, {"date": "2020-12-16", "server": 13, "serverRank": 54, "globalRank": 822, "totalPlayer": 1480}, {"date": "2020-12-18", "server": 22, "serverRank": 26, "globalRank": 1370, "totalPlayer": 1404}, {"date": "2020-12-19", "server": 12, "serverRank": "DNF", "globalRank": 764, "totalPlayer": 1256}, {"date": "2020-12-23", "server": 9, "serverRank": 29, "globalRank": 541, "totalPlayer": 1225}, {"date": "2020-12-24", "server": 8, "serverRank": 22, "globalRank": 470, "totalPlayer": 554}, {"date": "2020-12-27", "server": 18, "serverRank": 6, "globalRank": 1094, "totalPlayer": 1215}, {"date": "2020-12-28", "server": 8, "serverRank": 30, "globalRank": 478, "totalPlayer": 1271}, {"date": "2020-12-30", "server": 6, "serverRank": 9, "globalRank": 329, "totalPlayer": 1240}, {"date": "2021-01-01", "server": 8, "serverRank": 35, "globalRank": 483, "totalPlayer": 1135}, {"date": "2021-01-03", "server": 13, "serverRank": "DNF", "globalRank": 825, "totalPlayer": 1285}, {"date": "2021-01-04", "server": 5, "serverRank": 51, "globalRank": 307, "totalPlayer": 1349}, {"date": "2021-01-08", "server": 8, "serverRank": "DNF", "globalRank": 508, "totalPlayer": 1150}, {"date": "2021-01-14", "server": 22, "serverRank": "DNF", "globalRank": 1374, "totalPlayer": 1388}, {"date": "2021-04-20", "server": 22, "serverRank": "DNF", "globalRank": 1402, "totalPlayer": 2018}]}}