{"playerID": "dde6ac44-ae70-4f01-ba8a-9a7e8c7f2bfa", "playerNames": [{"playerName": "Maximfilms", "sinceDate": "2021-04-03"}], "results": {"cotd": [{"date": "2021-04-03", "server": 11, "serverRank": 29, "globalRank": 669, "totalPlayer": 1435}, {"date": "2021-04-07", "server": 15, "serverRank": 34, "globalRank": 930, "totalPlayer": 1947}, {"date": "2021-04-08", "server": 21, "serverRank": 16, "globalRank": 1296, "totalPlayer": 2019}, {"date": "2021-04-09", "server": 15, "serverRank": 37, "globalRank": 933, "totalPlayer": 1825}, {"date": "2021-05-05", "server": 13, "serverRank": 34, "globalRank": 802, "totalPlayer": 2716}, {"date": "2021-05-06", "server": 23, "serverRank": 25, "globalRank": 1433, "totalPlayer": 2583}, {"date": "2021-05-08", "server": 14, "serverRank": 29, "globalRank": 861, "totalPlayer": 1690}]}}