{"playerID": "df41fa87-998a-44c6-b578-d38c7c3df000", "playerNames": [{"playerName": "Knusperzapfen", "sinceDate": "2021-02-28"}], "results": {"cotd": [{"date": "2021-02-28", "server": 5, "serverRank": 49, "globalRank": 305, "totalPlayer": 1418}, {"date": "2021-03-15", "server": 11, "serverRank": 2, "globalRank": 642, "totalPlayer": 1706}, {"date": "2021-03-27", "server": 10, "serverRank": 12, "globalRank": 588, "totalPlayer": 1582}, {"date": "2021-03-29", "server": 5, "serverRank": 51, "globalRank": 307, "totalPlayer": 1676}, {"date": "2021-03-30", "server": 10, "serverRank": 56, "globalRank": 632, "totalPlayer": 1630}, {"date": "2021-04-18", "server": 7, "serverRank": 27, "globalRank": 411, "totalPlayer": 2063}]}}