{"playerID": "e555c2bd-4591-4503-bb8f-6896ad6a020e", "playerNames": [{"playerName": "Smiley_Riley43", "sinceDate": "2021-02-09"}], "results": {"cotd": [{"date": "2020-12-05", "server": 17, "serverRank": 8, "globalRank": 1032, "totalPlayer": 1322}, {"date": "2020-12-12", "server": 6, "serverRank": 59, "globalRank": 379, "totalPlayer": 1255}, {"date": "2021-04-05", "server": 16, "serverRank": 31, "globalRank": 991, "totalPlayer": 1288}, {"date": "2021-04-08", "server": 13, "serverRank": 30, "globalRank": 798, "totalPlayer": 2019}, {"date": "2021-04-13", "server": 13, "serverRank": 7, "globalRank": 775, "totalPlayer": 2119}, {"date": "2021-04-14", "server": 24, "serverRank": 1, "globalRank": 1473, "totalPlayer": 2178}, {"date": "2021-04-15", "server": 9, "serverRank": 31, "globalRank": 543, "totalPlayer": 2072}, {"date": "2021-04-19", "server": 8, "serverRank": 34, "globalRank": 482, "totalPlayer": 2141}, {"date": "2021-04-21", "server": 15, "serverRank": 9, "globalRank": 905, "totalPlayer": 2083}, {"date": "2021-04-29", "server": 16, "serverRank": 9, "globalRank": 969, "totalPlayer": 2424}]}}