{"playerID": "e5bbcabe-41b3-45dd-b70f-a3a345472801", "playerNames": [{"playerName": "Bandit_LT", "sinceDate": "2021-02-09"}, {"playerName": "Arnuxa20", "sinceDate": "2021-04-05"}], "results": {"cotd": [{"date": "2020-12-07", "server": 21, "serverRank": 34, "globalRank": 1314, "totalPlayer": 1595}, {"date": "2020-12-08", "server": 14, "serverRank": 57, "globalRank": 889, "totalPlayer": 1599}, {"date": "2020-12-09", "server": 17, "serverRank": 21, "globalRank": 1045, "totalPlayer": 1462}, {"date": "2020-12-13", "server": 20, "serverRank": 42, "globalRank": 1258, "totalPlayer": 1438}, {"date": "2020-12-15", "server": 18, "serverRank": 26, "globalRank": 1114, "totalPlayer": 1496}, {"date": "2020-12-17", "server": 16, "serverRank": 42, "globalRank": 1002, "totalPlayer": 1515}, {"date": "2020-12-20", "server": 18, "serverRank": 13, "globalRank": 1101, "totalPlayer": 1267}, {"date": "2020-12-27", "server": 10, "serverRank": "DNF", "globalRank": 637, "totalPlayer": 1215}, {"date": "2021-01-09", "server": 15, "serverRank": 14, "globalRank": 910, "totalPlayer": 1257}, {"date": "2021-01-10", "server": 13, "serverRank": 48, "globalRank": 816, "totalPlayer": 1357}, {"date": "2021-02-09", "server": 19, "serverRank": 18, "globalRank": 1170, "totalPlayer": 1395}, {"date": "2021-02-17", "server": 16, "serverRank": 27, "globalRank": 987, "totalPlayer": 1520}, {"date": "2021-04-05", "server": 12, "serverRank": 38, "globalRank": 742, "totalPlayer": 1288}, {"date": "2021-04-11", "server": 11, "serverRank": 34, "globalRank": 674, "totalPlayer": 1985}, {"date": "2021-04-24", "server": 15, "serverRank": 47, "globalRank": 943, "totalPlayer": 1954}, {"date": "2021-04-29", "server": 20, "serverRank": 15, "globalRank": 1231, "totalPlayer": 2424}, {"date": "2021-04-30", "server": 19, "serverRank": 10, "globalRank": 1162, "totalPlayer": 2209}, {"date": "2021-05-01", "server": 15, "serverRank": 16, "globalRank": 912, "totalPlayer": 2216}, {"date": "2021-05-02", "server": 16, "serverRank": 29, "globalRank": 989, "totalPlayer": 2264}, {"date": "2021-05-03", "server": 19, "serverRank": 38, "globalRank": 1190, "totalPlayer": 2662}, {"date": "2021-05-04", "server": 23, "serverRank": 10, "globalRank": 1418, "totalPlayer": 2656}, {"date": "2021-05-05", "server": 18, "serverRank": 15, "globalRank": 1103, "totalPlayer": 2716}]}}