{"playerID": "e70cb3ea-9df5-4e28-b1e9-566afe3aef04", "playerNames": [{"playerName": "rlvxpe", "sinceDate": "2021-02-09"}], "results": {"cotd": [{"date": "2021-02-07", "server": 9, "serverRank": "DNF", "globalRank": 572, "totalPlayer": 1374}, {"date": "2021-04-01", "server": 9, "serverRank": 52, "globalRank": 564, "totalPlayer": 1773}, {"date": "2021-04-03", "server": 9, "serverRank": 9, "globalRank": 521, "totalPlayer": 1435}, {"date": "2021-04-05", "server": 5, "serverRank": 17, "globalRank": 273, "totalPlayer": 1288}]}}