{"playerID": "ed578d74-21da-4d85-ab71-ee44627ec293", "playerNames": [{"playerName": "FreeSilentSam", "sinceDate": "2021-02-25"}], "results": {"cotd": [{"date": "2021-02-25", "server": 17, "serverRank": 5, "globalRank": 1029, "totalPlayer": 1491}, {"date": "2021-02-26", "server": 13, "serverRank": 26, "globalRank": 794, "totalPlayer": 1408}, {"date": "2021-02-27", "server": 15, "serverRank": "DNF", "globalRank": 958, "totalPlayer": 1111}, {"date": "2021-02-28", "server": 9, "serverRank": 36, "globalRank": 548, "totalPlayer": 1418}, {"date": "2021-03-01", "server": 16, "serverRank": 39, "globalRank": 999, "totalPlayer": 1607}, {"date": "2021-03-02", "server": 17, "serverRank": 40, "globalRank": 1064, "totalPlayer": 1689}, {"date": "2021-03-03", "server": 16, "serverRank": 29, "globalRank": 989, "totalPlayer": 1617}, {"date": "2021-03-04", "server": 12, "serverRank": 38, "globalRank": 742, "totalPlayer": 1705}, {"date": "2021-03-07", "server": 17, "serverRank": 26, "globalRank": 1050, "totalPlayer": 1680}, {"date": "2021-03-10", "server": 10, "serverRank": 26, "globalRank": 602, "totalPlayer": 1581}, {"date": "2021-03-11", "server": 13, "serverRank": 48, "globalRank": 816, "totalPlayer": 1705}, {"date": "2021-03-12", "server": 15, "serverRank": 18, "globalRank": 914, "totalPlayer": 1443}, {"date": "2021-03-13", "server": 10, "serverRank": 19, "globalRank": 595, "totalPlayer": 1220}, {"date": "2021-03-14", "server": 15, "serverRank": 23, "globalRank": 919, "totalPlayer": 1308}, {"date": "2021-03-15", "server": 16, "serverRank": 10, "globalRank": 970, "totalPlayer": 1706}, {"date": "2021-03-16", "server": 15, "serverRank": 44, "globalRank": 940, "totalPlayer": 1644}, {"date": "2021-03-17", "server": 13, "serverRank": 18, "globalRank": 786, "totalPlayer": 1683}, {"date": "2021-03-18", "server": 14, "serverRank": 44, "globalRank": 876, "totalPlayer": 1683}, {"date": "2021-03-19", "server": 16, "serverRank": 16, "globalRank": 976, "totalPlayer": 1595}, {"date": "2021-03-21", "server": 8, "serverRank": 45, "globalRank": 493, "totalPlayer": 1397}, {"date": "2021-03-22", "server": 15, "serverRank": 16, "globalRank": 912, "totalPlayer": 1748}, {"date": "2021-03-23", "server": 16, "serverRank": 32, "globalRank": 992, "totalPlayer": 1765}, {"date": "2021-03-24", "server": 9, "serverRank": 8, "globalRank": 520, "totalPlayer": 1806}, {"date": "2021-03-25", "server": 16, "serverRank": 19, "globalRank": 979, "totalPlayer": 1766}, {"date": "2021-03-26", "server": 9, "serverRank": 22, "globalRank": 534, "totalPlayer": 1600}, {"date": "2021-03-27", "server": 11, "serverRank": 13, "globalRank": 653, "totalPlayer": 1582}, {"date": "2021-03-28", "server": 11, "serverRank": 25, "globalRank": 665, "totalPlayer": 1517}, {"date": "2021-03-29", "server": 13, "serverRank": 5, "globalRank": 773, "totalPlayer": 1676}]}}