{"playerID": "f8bced51-9eb4-43f7-a148-eec3a2ad6c34", "playerNames": [{"playerName": "Exaeter", "sinceDate": "2021-02-09"}], "results": {"cotd": [{"date": "2021-02-06", "server": 7, "serverRank": 8, "globalRank": 392, "totalPlayer": 1080}, {"date": "2021-02-07", "server": 6, "serverRank": 2, "globalRank": 322, "totalPlayer": 1374}, {"date": "2021-02-08", "server": 8, "serverRank": 6, "globalRank": 454, "totalPlayer": 1533}, {"date": "2021-02-09", "server": 12, "serverRank": 40, "globalRank": 744, "totalPlayer": 1395}, {"date": "2021-02-10", "server": 12, "serverRank": 31, "globalRank": 735, "totalPlayer": 1523}, {"date": "2021-02-11", "server": 10, "serverRank": 54, "globalRank": 630, "totalPlayer": 1448}, {"date": "2021-02-12", "server": 9, "serverRank": 25, "globalRank": 537, "totalPlayer": 1376}, {"date": "2021-02-21", "server": 8, "serverRank": 12, "globalRank": 460, "totalPlayer": 1024}, {"date": "2021-02-27", "server": 4, "serverRank": 16, "globalRank": 208, "totalPlayer": 1111}, {"date": "2021-02-28", "server": 12, "serverRank": 11, "globalRank": 715, "totalPlayer": 1418}, {"date": "2021-03-07", "server": 14, "serverRank": 8, "globalRank": 840, "totalPlayer": 1680}, {"date": "2021-03-25", "server": 19, "serverRank": 10, "globalRank": 1162, "totalPlayer": 1766}, {"date": "2021-03-26", "server": 12, "serverRank": 46, "globalRank": 750, "totalPlayer": 1600}, {"date": "2021-03-28", "server": 10, "serverRank": 22, "globalRank": 598, "totalPlayer": 1517}, {"date": "2021-03-29", "server": 11, "serverRank": 11, "globalRank": 651, "totalPlayer": 1676}, {"date": "2021-03-30", "server": 12, "serverRank": 12, "globalRank": 716, "totalPlayer": 1630}, {"date": "2021-04-03", "server": 9, "serverRank": 5, "globalRank": 517, "totalPlayer": 1435}, {"date": "2021-04-09", "server": 11, "serverRank": 9, "globalRank": 649, "totalPlayer": 1825}, {"date": "2021-04-11", "server": 12, "serverRank": 12, "globalRank": 716, "totalPlayer": 1985}, {"date": "2021-04-12", "server": 18, "serverRank": 15, "globalRank": 1103, "totalPlayer": 2155}, {"date": "2021-04-13", "server": 10, "serverRank": 2, "globalRank": 578, "totalPlayer": 2119}, {"date": "2021-04-17", "server": 11, "serverRank": 28, "globalRank": 668, "totalPlayer": 1761}, {"date": "2021-04-18", "server": 7, "serverRank": 6, "globalRank": 390, "totalPlayer": 2063}, {"date": "2021-04-24", "server": 11, "serverRank": 15, "globalRank": 655, "totalPlayer": 1954}]}}