{"playerID": "fd9dcc25-2401-4443-a82b-978f15508498", "playerNames": [{"playerName": "LeGOoZoR", "sinceDate": "2021-02-09"}], "results": {"cotd": [{"date": "2020-11-22", "server": 9, "serverRank": 45, "globalRank": 557, "totalPlayer": 1551}, {"date": "2020-11-24", "server": 13, "serverRank": 24, "globalRank": 792, "totalPlayer": 1594}, {"date": "2020-12-08", "server": 10, "serverRank": "DNF", "globalRank": 578, "totalPlayer": 1599}, {"date": "2021-02-20", "server": 3, "serverRank": 29, "globalRank": 157, "totalPlayer": 1038}]}}