{"playerID": "fe0e9290-bd7a-436e-ab5c-ddedce4b4e08", "playerNames": [{"playerName": "nobiboTM", "sinceDate": "2021-02-09"}], "results": {"cotd": [{"date": "2020-11-19", "server": 2, "serverRank": 51, "globalRank": 115, "totalPlayer": 1624}, {"date": "2021-01-05", "server": 2, "serverRank": 55, "globalRank": 119, "totalPlayer": 1353}, {"date": "2021-01-19", "server": 4, "serverRank": 18, "globalRank": 210, "totalPlayer": 1413}, {"date": "2021-01-20", "server": 22, "serverRank": "DNF", "globalRank": 1396, "totalPlayer": 1432}, {"date": "2021-01-21", "server": 14, "serverRank": "DNF", "globalRank": 890, "totalPlayer": 1417}, {"date": "2021-01-25", "server": 3, "serverRank": 57, "globalRank": 185, "totalPlayer": 1504}, {"date": "2021-01-26", "server": 3, "serverRank": 4, "globalRank": 132, "totalPlayer": 1525}]}}